dandi/__init__.py
dandi/_version.py
dandi/consts.py
dandi/dandiapi.py
dandi/dandiarchive.py
dandi/dandiset.py
dandi/delete.py
dandi/download.py
dandi/due.py
dandi/exceptions.py
dandi/keyring_utils.py
dandi/misctypes.py
dandi/move.py
dandi/organize.py
dandi/pynwb_utils.py
dandi/pytest_plugin.py
dandi/upload.py
dandi/utils.py
dandi/validate.py
dandi/validate_types.py
dandi/bids_validator_deno/__init__.py
dandi/bids_validator_deno/_models.py
dandi/bids_validator_deno/_validator.py
dandi/cli/__init__.py
dandi/cli/base.py
dandi/cli/cmd_delete.py
dandi/cli/cmd_digest.py
dandi/cli/cmd_download.py
dandi/cli/cmd_instances.py
dandi/cli/cmd_ls.py
dandi/cli/cmd_move.py
dandi/cli/cmd_organize.py
dandi/cli/cmd_service_scripts.py
dandi/cli/cmd_shell_completion.py
dandi/cli/cmd_upload.py
dandi/cli/cmd_validate.py
dandi/cli/command.py
dandi/cli/formatter.py
dandi/cli/tests/__init__.py
dandi/cli/tests/test_cmd_ls.py
dandi/cli/tests/test_cmd_validate.py
dandi/cli/tests/test_command.py
dandi/cli/tests/test_digest.py
dandi/cli/tests/test_download.py
dandi/cli/tests/test_formatter.py
dandi/cli/tests/test_instances.py
dandi/cli/tests/test_move.py
dandi/cli/tests/test_service_scripts.py
dandi/cli/tests/test_shell_completion.py
dandi/cli/tests/data/update_dandiset_from_doi/biorxiv.json
dandi/cli/tests/data/update_dandiset_from_doi/biorxiv.vcr.yaml
dandi/cli/tests/data/update_dandiset_from_doi/elife.json
dandi/cli/tests/data/update_dandiset_from_doi/elife.vcr.yaml
dandi/cli/tests/data/update_dandiset_from_doi/jneurosci.json
dandi/cli/tests/data/update_dandiset_from_doi/jneurosci.vcr.yaml
dandi/cli/tests/data/update_dandiset_from_doi/nature.json
dandi/cli/tests/data/update_dandiset_from_doi/nature.vcr.yaml
dandi/cli/tests/data/update_dandiset_from_doi/neuron.json
dandi/cli/tests/data/update_dandiset_from_doi/neuron.vcr.yaml
dandi/files/__init__.py
dandi/files/_private.py
dandi/files/bases.py
dandi/files/bids.py
dandi/files/zarr.py
dandi/metadata/__init__.py
dandi/metadata/core.py
dandi-0.74.2.dist-info/licenses/LICENSE
dandi-0.74.2.dist-info/METADATA
dandi-0.74.2.dist-info/WHEEL
dandi-0.74.2.dist-info/entry_points.txt
dandi-0.74.2.dist-info/top_level.txt
dandi-0.74.2.dist-info/RECORD
