Metadata-Version: 2.4
Name: dandi
Version: 0.74.2
Summary: Command line client for interaction with DANDI instances
Author-email: DANDI developers <team@dandiarchive.org>
Maintainer-email: DANDI developers <team@dandiarchive.org>
License:                                  Apache License
Project-URL: Homepage, http://dandiarchive.org
Project-URL: Source Code, https://github.com/dandi/dandi-cli
Project-URL: Documentation, https://dandi.readthedocs.io
Keywords: data standards,data organization,BIDS,Brain Imaging Data Structure,NWB,NeurodataWithoutBorders,DANDI Archive,neurodata,neuroscience,neurophysiology,NIH,BRAIN Initiative
Classifier: Development Status :: 4 - Beta
Classifier: Environment :: Console
Classifier: Intended Audience :: Science/Research
Classifier: License :: OSI Approved :: Apache Software License
Classifier: Operating System :: OS Independent
Classifier: Programming Language :: Python
Classifier: Programming Language :: Python :: 3.10
Classifier: Programming Language :: Python :: 3.11
Classifier: Programming Language :: Python :: 3.12
Classifier: Programming Language :: Python :: 3.13
Classifier: Topic :: Scientific/Engineering
Requires-Python: >=3.10
License-File: LICENSE
Requires-Dist: bidsschematools~=1.0
Requires-Dist: bids-validator-deno>=2.0.5
Requires-Dist: click<8.2.0,>=7.1
Requires-Dist: click-didyoumean
Requires-Dist: dandischema~=0.12.0
Requires-Dist: etelemetry>=0.2.2
Requires-Dist: fasteners
Requires-Dist: fscacher>=0.3.0
Requires-Dist: h5py<3.15; sys_platform == "darwin" and platform_machine != "arm64"
Requires-Dist: h5py; sys_platform != "darwin" or platform_machine == "arm64"
Requires-Dist: hdmf!=3.14.4,!=3.5.0
Requires-Dist: humanize
Requires-Dist: interleave~=0.3
Requires-Dist: joblib
Requires-Dist: keyring!=23.9.0
Requires-Dist: keyrings.alt
Requires-Dist: packaging
Requires-Dist: platformdirs
Requires-Dist: pycryptodomex
Requires-Dist: pydantic~=2.0
Requires-Dist: pynwb!=1.1.0,!=2.3.0,>=1.0.3
Requires-Dist: numcodecs<0.16
Requires-Dist: nwbinspector!=0.4.32,>=0.4.28
Requires-Dist: pyout!=0.6.0,>=0.5
Requires-Dist: python-dateutil
Requires-Dist: requests~=2.20
Requires-Dist: ruamel.yaml<1,>=0.15
Requires-Dist: semantic-version
Requires-Dist: tenacity
Requires-Dist: tensorstore
Requires-Dist: urllib3>=2.0.0
Requires-Dist: yarl~=1.9
Requires-Dist: zarr<=3.1.5,>=2.10
Requires-Dist: zarr_checksum~=0.4.0
Provides-Extra: extensions
Requires-Dist: allensdk; extra == "extensions"
Requires-Dist: ndx-hed; extra == "extensions"
Requires-Dist: ndx-events; extra == "extensions"
Provides-Extra: extras
Requires-Dist: duecredit>=0.6.0; extra == "extras"
Requires-Dist: fsspec[http]; extra == "extras"
Provides-Extra: style
Requires-Dist: flake8; extra == "style"
Requires-Dist: pre-commit; extra == "style"
Provides-Extra: test
Requires-Dist: anys~=0.2; extra == "test"
Requires-Dist: coverage; extra == "test"
Requires-Dist: opencv-python; extra == "test"
Requires-Dist: pytest; extra == "test"
Requires-Dist: pytest-cov; extra == "test"
Requires-Dist: pytest-mock; extra == "test"
Requires-Dist: pytest-rerunfailures; extra == "test"
Requires-Dist: pytest-timeout; extra == "test"
Requires-Dist: responses!=0.24.0,!=0.25.5; extra == "test"
Requires-Dist: vcrpy; extra == "test"
Provides-Extra: tools
Requires-Dist: boto3; extra == "tools"
Provides-Extra: all
Requires-Dist: dandi[extensions]; extra == "all"
Requires-Dist: dandi[extras]; extra == "all"
Requires-Dist: dandi[style]; extra == "all"
Requires-Dist: dandi[test]; extra == "all"
Requires-Dist: dandi[tools]; extra == "all"
Dynamic: license-file
